[
  {
    "inputs": [
      {
        "internalType": "string",
        "name": "_domain",
        "type": "string"
      },
      {
        "internalType": "address",
        "name": "_domainOwner",
        "type": "address"
      }
    ],
    "stateMutability": "nonpayable",
    "type": "constructor"
  },
  {
    "anonymous": false,
    "inputs": [
      {
        "indexed": true,
        "internalType": "address",
        "name": "previousOwner",
        "type": "address"
      },
      {
        "indexed": true,
        "internalType": "address",
        "name": "newOwner",
        "type": "address"
      }
    ],
    "name": "OwnershipTransferred",
    "type": "event"
  },
  {
    "inputs": [
      {
        "internalType": "string",
        "name": "_subDomain",
        "type": "string"
      },
      {
        "internalType": "string",
        "name": "_description",
        "type": "string"
      },
      {
        "internalType": "string",
        "name": "_website",
        "type": "string"
      },
      {
        "internalType": "string",
        "name": "_email",
        "type": "string"
      },
      {
        "internalType": "string",
        "name": "_avatar",
        "type": "string"
      }
    ],
    "name": "changeSubDomainData",
    "outputs": [],
    "stateMutability": "nonpayable",
    "type": "function"
  },
  {
    "inputs": [
      {
        "internalType": "string",
        "name": "_subDomain",
        "type": "string"
      }
    ],
    "name": "deleteSubDomain",
    "outputs": [],
    "stateMutability": "nonpayable",
    "type": "function"
  },
  {
    "inputs": [],
    "name": "getAllSubDomains",
    "outputs": [
      {
        "internalType": "string[]",
        "name": "",
        "type": "string[]"
      }
    ],
    "stateMutability": "view",
    "type": "function"
  },
  {
    "inputs": [
      {
        "internalType": "address",
        "name": "",
        "type": "address"
      }
    ],
    "name": "hasSubDomain",
    "outputs": [
      {
        "internalType": "bool",
        "name": "",
        "type": "bool"
      }
    ],
    "stateMutability": "view",
    "type": "function"
  },
  {
    "inputs": [
      {
        "internalType": "string",
        "name": "",
        "type": "string"
      }
    ],
    "name": "isDomainActive",
    "outputs": [
      {
        "internalType": "bool",
        "name": "",
        "type": "bool"
      }
    ],
    "stateMutability": "view",
    "type": "function"
  },
  {
    "inputs": [],
    "name": "owner",
    "outputs": [
      {
        "internalType": "address",
        "name": "",
        "type": "address"
      }
    ],
    "stateMutability": "view",
    "type": "function"
  },
  {
    "inputs": [],
    "name": "ownerInfo",
    "outputs": [
      {
        "internalType": "address",
        "name": "owner",
        "type": "address"
      },
      {
        "internalType": "string",
        "name": "description",
        "type": "string"
      },
      {
        "internalType": "string",
        "name": "website",
        "type": "string"
      },
      {
        "internalType": "string",
        "name": "email",
        "type": "string"
      },
      {
        "internalType": "string",
        "name": "avatar",
        "type": "string"
      }
    ],
    "stateMutability": "view",
    "type": "function"
  },
  {
    "inputs": [],
    "name": "parentDomain",
    "outputs": [
      {
        "internalType": "string",
        "name": "",
        "type": "string"
      }
    ],
    "stateMutability": "view",
    "type": "function"
  },
  {
    "inputs": [
      {
        "internalType": "string",
        "name": "",
        "type": "string"
      }
    ],
    "name": "registered",
    "outputs": [
      {
        "internalType": "bool",
        "name": "",
        "type": "bool"
      }
    ],
    "stateMutability": "view",
    "type": "function"
  },
  {
    "inputs": [],
    "name": "registryContractAddr",
    "outputs": [
      {
        "internalType": "address",
        "name": "",
        "type": "address"
      }
    ],
    "stateMutability": "view",
    "type": "function"
  },
  {
    "inputs": [],
    "name": "renounceOwnership",
    "outputs": [],
    "stateMutability": "nonpayable",
    "type": "function"
  },
  {
    "inputs": [
      {
        "internalType": "string",
        "name": "_subDomain",
        "type": "string"
      }
    ],
    "name": "setNewSubdomain",
    "outputs": [],
    "stateMutability": "nonpayable",
    "type": "function"
  },
  {
    "inputs": [
      {
        "internalType": "string",
        "name": "_description",
        "type": "string"
      },
      {
        "internalType": "string",
        "name": "_website",
        "type": "string"
      },
      {
        "internalType": "string",
        "name": "_email",
        "type": "string"
      },
      {
        "internalType": "string",
        "name": "_avatar",
        "type": "string"
      }
    ],
    "name": "setOwnerData",
    "outputs": [],
    "stateMutability": "nonpayable",
    "type": "function"
  },
  {
    "inputs": [
      {
        "internalType": "string",
        "name": "",
        "type": "string"
      }
    ],
    "name": "subDomainData",
    "outputs": [
      {
        "internalType": "address",
        "name": "owner",
        "type": "address"
      },
      {
        "internalType": "string",
        "name": "description",
        "type": "string"
      },
      {
        "internalType": "string",
        "name": "website",
        "type": "string"
      },
      {
        "internalType": "string",
        "name": "email",
        "type": "string"
      },
      {
        "internalType": "string",
        "name": "avatar",
        "type": "string"
      }
    ],
    "stateMutability": "view",
    "type": "function"
  },
  {
    "inputs": [
      {
        "internalType": "uint256",
        "name": "",
        "type": "uint256"
      }
    ],
    "name": "subDomainsList",
    "outputs": [
      {
        "internalType": "string",
        "name": "",
        "type": "string"
      }
    ],
    "stateMutability": "view",
    "type": "function"
  },
  {
    "inputs": [
      {
        "internalType": "address",
        "name": "_newOwner",
        "type": "address"
      }
    ],
    "name": "transfer",
    "outputs": [],
    "stateMutability": "nonpayable",
    "type": "function"
  },
  {
    "inputs": [
      {
        "internalType": "address",
        "name": "newOwner",
        "type": "address"
      }
    ],
    "name": "transferOwnership",
    "outputs": [],
    "stateMutability": "nonpayable",
    "type": "function"
  },
  {
    "inputs": [
      {
        "internalType": "string",
        "name": "_subDomain",
        "type": "string"
      },
      {
        "internalType": "address",
        "name": "_newOwner",
        "type": "address"
      }
    ],
    "name": "transferSubDomain",
    "outputs": [],
    "stateMutability": "nonpayable",
    "type": "function"
  }
]
